analyze.py
area.py
check_update.py
create_f2k.py
database.py
design.py
etabs_obj.py
find_etabs.py
frame_obj.py
freecad_funcs.py
group.py
load_cases.py
load_combinations.py
load_patterns.py
material.py
points.py
prop_frame.py
results.py
select_obj.py
story.py
view.py
sections/sections.py
etabs_api-1.2.dist-info/METADATA
etabs_api-1.2.dist-info/WHEEL
etabs_api-1.2.dist-info/licenses/LICENSE
etabs_api-1.2.dist-info/RECORD
