Metadata-Version: 2.1
Name: etabs_api
Version: 1.2
Summary: API for CSI ETABS 2018 and Higher
Project-URL: Homepage, https://github.com/ebrahimraeyat/etabs_api
Author-email: Raeyat Roknabadi Ebrahim <ebe79442114@yahoo.com>
License-File: LICENSE
Classifier: License :: OSI Approved :: GNU General Public License v2 (GPLv2)
Classifier: Operating System :: Microsoft :: Windows
Classifier: Programming Language :: Python :: 3
Requires-Python: >=3.8
Requires-Dist: comtypes
Requires-Dist: numpy
Requires-Dist: pandas
Requires-Dist: psutil
